notihub/__init__.py
notihub/base_notifier.py
notihub/client.py
notihub/notifiers/__init__.py
notihub/notifiers/aws/__init__.py
notihub/notifiers/aws/notifier.py
notihub/notifiers/aws/clients/__init__.py
notihub/notifiers/aws/clients/base_aws_client.py
notihub/notifiers/aws/clients/pinpoint_client.py
notihub/notifiers/aws/clients/ses_client.py
notihub/notifiers/aws/clients/sns_client.py
notihub/notifiers/twilio/__init__.py
notihub/notifiers/twilio/notifier.py
notihub-0.1.8rc0.dist-info/METADATA
notihub-0.1.8rc0.dist-info/WHEEL
notihub-0.1.8rc0.dist-info/licenses/LICENSE
notihub-0.1.8rc0.dist-info/RECORD
