Metadata-Version: 2.4
Name: notihub
Version: 0.1.8rc0
Summary: Notihub is a Python library to manage and use different notification services.
Project-URL: Homepage, https://github.com/Alternova-Inc/notihub
Project-URL: Repository, https://github.com/Alternova-Inc/notihub
Author-email: Juan Trujillo <juan.trujillo@alternova.com>
License: MIT License
License-File: LICENSE
Keywords: aws,notifications
Classifier: Development Status :: 3 - Alpha
Classifier: Intended Audience :: Developers
Classifier: License :: OSI Approved :: MIT License
Classifier: Operating System :: OS Independent
Classifier: Programming Language :: Python :: 3
Classifier: Programming Language :: Python :: 3.10
Classifier: Programming Language :: Python :: 3.11
Classifier: Programming Language :: Python :: 3.12
Classifier: Topic :: Software Development :: Libraries :: Python Modules
Requires-Python: >=3.8
Requires-Dist: boto3<2,>=1.20.0
Requires-Dist: coverage>=7.6.1
Requires-Dist: dotenv<0.10,>=0.9.9
Requires-Dist: pytest-cov>=5.0.0
Requires-Dist: pytest-xdist>=3.6.1
Requires-Dist: pytest>=8.3.5
Requires-Dist: python-decouple>=3.8
Provides-Extra: dev
